README.md
setup.py
amoex/__init__.py
amoex/base.py
amoex/shares.py
amoex/utils.py
amoex.egg-info/PKG-INFO
amoex.egg-info/SOURCES.txt
amoex.egg-info/dependency_links.txt
amoex.egg-info/requires.txt
amoex.egg-info/top_level.txt