Metadata-Version: 1.1
Name: amoex
Version: 0.0.3
Summary: Asyncio MOEX Python API
Home-page: https://github.com/prokaktus/amoex
Author: Filipenko Maxim
Author-email: mfilipenko@yandex.ru
License: UNKNOWN
Platform: UNKNOWN
Classifier: Programming Language :: Python
Classifier: Programming Language :: Python :: 3
Classifier: Programming Language :: Python :: 3.5
Classifier: Programming Language :: Python :: 3.6
Classifier: Programming Language :: Python :: 3.7
